chasm/__init__.py
chasm/chasm.py
chasm/cli.py
chasm-0.1.0.dist-info/AUTHORS.rst
chasm-0.1.0.dist-info/LICENSE
chasm-0.1.0.dist-info/METADATA
chasm-0.1.0.dist-info/WHEEL
chasm-0.1.0.dist-info/entry_points.txt
chasm-0.1.0.dist-info/top_level.txt
chasm-0.1.0.dist-info/RECORD
