Metadata-Version: 2.1
Name: chasm
Version: 0.1.0
Summary: improved chemi-compiler-compiler for goonstation
Home-page: https://github.com/j-awn/chasm
Author: jawn
Author-email: j-awn@planetmail.net
License: MIT license
Keywords: chasm
Platform: UNKNOWN
Classifier: Development Status :: 2 - Pre-Alpha
Classifier: Intended Audience :: Developers
Classifier: License :: OSI Approved :: MIT License
Classifier: Natural Language :: English
Classifier: Programming Language :: Python :: 3
Classifier: Programming Language :: Python :: 3.6
Classifier: Programming Language :: Python :: 3.7
Classifier: Programming Language :: Python :: 3.8
Requires-Python: >=3.6
